{
	"version": "2",
	"author": "Phaedrus",
	"authorURL": "https://github.com/Phaedrus3",
	"supportURL": "",
	"mods": [
		{
			"type": "mod",
			"version": "2.0",
			"name": "SmallFixToScenes",
			"displayName": "Small Fix To Scenes",
			"author": "",
			"previousAuthors": "Santana",
			"released": "2023-06-26",
			"updated": "2023-06-26",
			"downloadURL": "https://github.com/Phaedrus3/SmallFixToScenes/releases/download/v2.0/SmallFixToScenes.dll",
			"modURL": "https://github.com/Phaedrus3/SmallFixToScenes",
			"description": "Remove beds, cabinets, counters and a few other objects in the Lookout Towers (ML, CH and BI) and the stone cabins (TWM and BRR).",
			"tags": "",
			"categories": [
				"Quality of Life",
				"Base Building"
			],
			"gameversion": [],
			"images": [
				"https://github.com/Phaedrus3/SmallFixToScenes/raw/main/smallfixtoscenes.jpg"
			],
			"dependencies": [
				"ModSettings"
			],
			"status": {
				"working": true,
				"beta": false,
				"patchnotes": "FIX: Fixed for TLD 2.17\nNEW: Added Forestry Lookout in ML\nNEW: Added Pensive Lookout in BI\nNEW: Added Brick Layers Retreat in BRR",
				"notes": "",
				"issues": ""
			},
			"testedon": {
				"tldversion": "2.17",
				"mlversion": " 0.6.1"
			},
			"updater": {
				"enable": true,
				"downloads": []
			},
			"aliases": []
		},
		{
			"type": "mod",
			"version": "2.0",
			"name": "Stretch Armstrong",
			"displayName": "Stretch Armstrong",
			"author": "",
			"previousAuthors": "Bushtail",
			"released": "2023-06-27",
			"updated": "2023-06-27",
			"downloadURL": "https://github.com/Phaedrus3/StretchArmstrong/releases/download/v2.0/StretchArmstrong.dll",
			"modURL": "https://github.com/Phaedrus3/StretchArmstrong",
			"description": "Allows the user to modify their interaction distance.",
			"tags": "",
			"categories": [
				"Quality of Life",
				"Gameplay"
			],
			"gameversion": [],
			"images": [],
			"dependencies": [
				"ModSettings"
			],
			"status": {
				"working": true,
				"beta": false,
				"patchnotes": "",
				"notes": "",
				"issues": ""
			},
			"testedon": {
				"tldversion": "2.17",
				"mlversion": "0.6.1"
			},
			"updater": {
				"enable": false,
				"downloads": []
			},
			"aliases": []
		},
		{
			"type": "mod",
			"version": "2.1.0",
			"name": "SonicMode",
			"displayName": "SonicMode",
			"author": "",
			"previousAuthors": "ds5678",
			"released": "2023-07-09",
			"updated": "2023-07-09",
			"downloadURL": "https://github.com/Phaedrus3/SonicMode/releases/download/v2.1.0/SonicMode.dll",
			"modURL": "https://github.com/Phaedrus3/SonicMode",
			"description": "Lets you go fast!",
			"tags": "",
			"categories": [
				"Quality of Life",
				"Gameplay"
			],
			"gameversion": [],
			"images": [],
			"dependencies": [
				"ModSettings"
			],
			"status": {
				"working": true,
				"beta": false,
				"patchnotes": "",
				"notes": "",
				"issues": ""
			},
			"testedon": {
				"tldversion": "2.17",
				"mlversion": "0.6.1"
			},
			"updater": {
				"enable": true,
				"downloads": []
			},
			"aliases": []
		},
		{
			"type": "mod",
			"version": "1.2",
			"name": "Increase Save Slot Limit",
			"displayName": "Increase Save Slot Limit",
			"author": "Phaedrus",
			"previousAuthors": "ds5678 and zeobviouslyfakeacc",
			"released": "2023-07-09",
			"updated": "2023-07-09",
			"downloadURL": "https://github.com/Phaedrus3/IncreaseSaveSlotLimit/releases/download/v1.2/IncreaseSaveSlotLimit.dll",
			"modURL": "https://github.com/Phaedrus3/IncreaseSaveSlotLimit",
			"description": "Increases save slots to 999 instead of the default 25.",
			"tags": "",
			"categories": [
				"Quality of Life"
			],
			"gameversion": [],
			"images": [],
			"dependencies": [],
			"status": {
				"working": true,
				"beta": false,
				"patchnotes": "",
				"notes": "",
				"issues": ""
			},
			"testedon": {
				"tldversion": "2.17",
				"mlversion": "0.6.1"
			},
			"updater": {
				"enable": true,
				"downloads": []
			},
			"aliases": []
		},
		{
			"type": "mod",
			"version": "1.0",
			"name": "Fort Blackrock: A Blackrock Prison Cleanup",
			"displayName": "Fort Blackrock: A Blackrock Prison Cleanup",
			"author": "Phaedrus, FarCryBliss",
			"previousAuthors": "",
			"released": "2023-08-01",
			"updated": "2023-08-01",
			"downloadURL": "https://github.com/Phaedrus3/BetterBlackrockPrison/releases/download/v1.0/BetterBlackrock.dll",
			"modURL": "https://github.com/Phaedrus3/BetterBlackrockPrison",
			"description": "Special Thanks to FarCryBliss!!  Clearing out the rubble was hard for the survivors that chose to turn Blackrock Prison into a home for themselves. A fortress in the snowy region of Blackrock, Fort Blackrock is now a large open player home with all but 1 jail cell open, a clear main hallway and the canteen originally full of rubble that you have to crouch to get through has been cleared, able to be used for anything a survivor might want. We don't have a palace in The Long Dark but this comes close.",
			"tags": "",
			"categories": [
				"Quality of Life",
				"Base Building"
			],
			"gameversion": [],
			"images": [
				"https://github.com/Phaedrus3/ModListJson/raw/main/Fort_Blackrock2.jpg"
			],
			"dependencies": [],
			"status": {
				"working": true,
				"beta": false,
				"patchnotes": "",
				"notes": "",
				"issues": ""
			},
			"testedon": {
				"tldversion": "2.22",
				"mlversion": "0.6.1"
			},
			"updater": {
				"enable": true,
				"downloads": []
			},
			"aliases": []
		}
	]
}


